marinerg_test_access/__init__.py
marinerg_test_access/admin.py
marinerg_test_access/apps.py
marinerg_test_access/py.typed
marinerg_test_access/urls.py
marinerg_test_access/client/__init__.py
marinerg_test_access/client/client.py
marinerg_test_access/migrations/0001_initial.py
marinerg_test_access/migrations/0002_accessapplicationboardreview_application_and_more.py
marinerg_test_access/migrations/0003_rename_creator_accessapplicationboarddecision_reviewer_and_more.py
marinerg_test_access/migrations/0004_remove_accessapplicationboarddecision_call.py
marinerg_test_access/migrations/0005_facilitytestreport_facility_and_more.py
marinerg_test_access/migrations/0006_remove_facilitytestreport_dataset_uri_and_more.py
marinerg_test_access/migrations/0007_alter_facilitytestreport_datasets.py
marinerg_test_access/migrations/__init__.py
marinerg_test_access/models/__init__.py
marinerg_test_access/models/access_call.py
marinerg_test_access/models/application.py
marinerg_test_access/models/reviews.py
marinerg_test_access/models/summary.py
marinerg_test_access/serializers/__init__.py
marinerg_test_access/serializers/access_call.py
marinerg_test_access/serializers/application.py
marinerg_test_access/serializers/reviews.py
marinerg_test_access/utils/__init__.py
marinerg_test_access/utils/test_utils/__init__.py
marinerg_test_access/utils/test_utils/models.py
marinerg_test_access/utils/test_utils/resources.py
marinerg_test_access/utils/test_utils/test_client.py
marinerg_test_access/view_sets/__init__.py
marinerg_test_access/view_sets/access_call.py
marinerg_test_access/view_sets/application.py
marinerg_test_access/view_sets/reviews.py
marinerg_test_access-0.0.16.dist-info/licenses/LICENSE
marinerg_test_access-0.0.16.dist-info/METADATA
marinerg_test_access-0.0.16.dist-info/WHEEL
marinerg_test_access-0.0.16.dist-info/entry_points.txt
marinerg_test_access-0.0.16.dist-info/top_level.txt
marinerg_test_access-0.0.16.dist-info/RECORD
