Metadata-Version: 2.4
Name: marinerg_test_access
Version: 0.0.16
Summary: A web app for project access applications.
Author-email: Irish Centre for High End Computing <james.grogan@ichec.ie>
Project-URL: Repository, https://git.ichec.ie/marinerg-i/test-access-service
Project-URL: Homepage, https://git.ichec.ie/marinerg-i/test-access-service
Keywords: Web Application,Django
Classifier: Development Status :: 3 - Alpha
Classifier: Programming Language :: Python :: 3
Classifier: Operating System :: OS Independent
Requires-Python: >=3.10
License-File: LICENSE
Requires-Dist: marinerg_data_access==0.0.10
Requires-Dist: weasyprint
Provides-Extra: test
Requires-Dist: pytest; extra == "test"
Requires-Dist: pytest-cov; extra == "test"
Requires-Dist: pytest-sugar; extra == "test"
Requires-Dist: beautifulsoup4; extra == "test"
Requires-Dist: black; extra == "test"
Requires-Dist: flake8; extra == "test"
Requires-Dist: pylint; extra == "test"
Requires-Dist: mypy; extra == "test"
Requires-Dist: requests; extra == "test"
Requires-Dist: types-requests; extra == "test"
Provides-Extra: container
Requires-Dist: psycopg2-binary; extra == "container"
Requires-Dist: gunicorn; extra == "container"
Provides-Extra: types
Requires-Dist: types-requests; extra == "types"
Requires-Dist: types-PyYAML; extra == "types"
Dynamic: license-file
